setup.py
hall_cond/__init__.py
hall_cond/hall_conductivity.py
hall_cond/ifinsu.py
hall_cond.egg-info/PKG-INFO
hall_cond.egg-info/SOURCES.txt
hall_cond.egg-info/dependency_links.txt
hall_cond.egg-info/requires.txt
hall_cond.egg-info/top_level.txt