Metadata-Version: 1.0
Name: hall-cond
Version: 0.1.0
Summary: A Lightweight Hall Conductivity Computational Library
Home-page: UNKNOWN
Author: UNKNOWN
Author-email: UNKNOWN
License: GPLv3 or later
Platform: UNKNOWN
